{
  "_class": "shapeGroup",
  "clippingMaskMode": 0,
  "do_objectID": "22EF5C78-1C16-446E-9A06-895DD039EE7C",
  "exportOptions": {
    "_class": "exportOptions",
    "do_objectID": "0E81E3F4-1C79-493F-AD30-084107FC8368",
    "exportFormats": [
    ],
    "includedLayerIds": [
    ],
    "layerOptions": 0,
    "shouldTrim": false
  },
  "frame": {
    "_class": "rect",
    "constrainProportions": false,
    "do_objectID": "01ED0309-3F14-479A-901A-DE285FD0A742",
    "height": 2,
    "width": 210,
    "x": 15,
    "y": 335
  },
  "hasClickThrough": false,
  "hasClippingMask": false,
  "isFlippedHorizontal": false,
  "isFlippedVertical": false,
  "isLocked": false,
  "isVisible": true,
  "layerListExpandedType": 1,
  "layers": [
    {
      "class": "rectangle",
      "id": "0EED4695-D487-48BA-989A-CEFEFF62BD82"
    }
  ],
  "name": "Rectangle 6",
  "nameIsFixed": false,
  "resizingConstraint": 63,
  "resizingType": 0,
  "rotation": 0,
  "shouldBreakMaskChain": false,
  "style": {
    "_class": "style",
    "borders": [
      {
        "_class": "border",
        "color": {
          "_class": "color",
          "alpha": 1,
          "blue": 0.592,
          "green": 0.592,
          "red": 0.592
        },
        "fillType": 0,
        "isEnabled": false,
        "position": 1,
        "thickness": 1
      }
    ],
    "do_objectID": "D151E54F-5912-4DF8-B57D-CD8D3FFBCA8C",
    "endDecorationType": 0,
    "fills": [
      {
        "_class": "fill",
        "color": {
          "_class": "color",
          "alpha": 1,
          "blue": 0.9686274509803922,
          "green": 0.9686274509803922,
          "red": 0.9686274509803922
        },
        "fillType": 0,
        "isEnabled": true,
        "noiseIndex": 0,
        "noiseIntensity": 0,
        "patternFillType": 1,
        "patternTileScale": 1
      }
    ],
    "miterLimit": 10,
    "startDecorationType": 0
  },
  "windingRule": 1
}