{
  "_class": "text",
  "attributedString": {
    "_class": "attributedString",
    "attributes": [
      {
        "_class": "stringAttribute",
        "attributes": {
          "MSAttributedStringColorAttribute": {
            "_class": "color",
            "alpha": 1,
            "blue": 0.9372549019607843,
            "green": 0.6823529411764708,
            "red": 0
          },
          "MSAttributedStringFontAttribute": {
            "_class": "fontDescriptor",
            "attributes": {
              "name": "Lato-Bold",
              "size": 14
            }
          },
          "kerning": 0.4375,
          "paragraphStyle": {
            "_class": "paragraphStyle"
          }
        },
        "length": 17,
        "location": 0
      }
    ],
    "string": "Baca Selengkapnya"
  },
  "automaticallyDrawOnUnderlyingPath": false,
  "do_objectID": "21B100BE-CF0D-4A68-A726-9007B22D43FD",
  "dontSynchroniseWithSymbol": false,
  "exportOptions": {
    "_class": "exportOptions",
    "do_objectID": "C8DB75B6-0C68-47D0-B7F0-DB72C227EA91",
    "exportFormats": [
    ],
    "includedLayerIds": [
    ],
    "layerOptions": 0,
    "shouldTrim": false
  },
  "frame": {
    "_class": "rect",
    "constrainProportions": false,
    "do_objectID": "2B098D96-1F25-4997-B90E-EAEB6D4FFC83",
    "height": 20,
    "width": 150,
    "x": 37,
    "y": 1048
  },
  "glyphBounds": "{{1, 3}, {125, 14}}",
  "isFlippedHorizontal": false,
  "isFlippedVertical": false,
  "isLocked": false,
  "isVisible": true,
  "layerListExpandedType": 0,
  "lineSpacingBehaviour": 2,
  "name": "Baca Selengkapnya",
  "nameIsFixed": false,
  "resizingConstraint": 63,
  "resizingType": 0,
  "rotation": 0,
  "shouldBreakMaskChain": false,
  "style": {
    "_class": "style",
    "do_objectID": "29E36A2C-CC8D-4107-9EA7-AB96975DA0D6",
    "endDecorationType": 0,
    "miterLimit": 10,
    "startDecorationType": 0,
    "textStyle": {
      "_class": "textStyle",
      "do_objectID": "FCB8E7BB-1886-47FF-AF68-FC4798151ECE",
      "encodedAttributes": {
        "MSAttributedStringColorAttribute": {
          "_class": "color",
          "alpha": 1,
          "blue": 0.9372549019607843,
          "green": 0.6823529411764708,
          "red": 0
        },
        "MSAttributedStringFontAttribute": {
          "_class": "fontDescriptor",
          "attributes": {
            "name": "Lato-Bold",
            "size": 14
          }
        },
        "kerning": 0.4375,
        "paragraphStyle": {
          "_class": "paragraphStyle"
        }
      },
      "verticalAlignment": 0
    }
  },
  "textBehaviour": 2
}